[
  {
    "id": 101,
    "name": "Amy",
    "schedule": [
      {
        "date": "2021-05-31",
        "start": "5:58:00",
        "end": "10:00:00"
      },
      {
        "date": "2021-05-22",
        "start": "9:00:00",
        "end": "17:00:00"
      },
      {
        "date": "2021-05-29",
        "start": "9:00:00",
        "end": "17:00:00"
      },
      {
        "date": "2021-05-31",
        "start": "9:00:00",
        "end": "17:00:00"
      }
    ]
  },
  {
    "id": 102,
    "name": "Bob",
    "schedule": [
      {
        "date": "2021-05-21",
        "start": "13:00:00",
        "end": "17:00:00"
      },
      {
        "date": "2021-05-22",
        "start": "13:00:00",
        "end": "17:00:00"
      },
      {
        "date": "2021-05-23",
        "start": "13:00:00",
        "end": "17:00:00"
      },
      {
        "date": "2021-05-24",
        "start": "13:00:00",
        "end": "17:00:00"
      }
    ]
  },
  {
    "id": 103,
    "name": "Clare",
    "schedule": [
      {
        "date": "2021-05-21",
        "start": "9:00:00",
        "end": "12:00:00"
      },
      {
        "date": "2021-05-22",
        "start": "10:00:00",
        "end": "14:00:00"
      },
      {
        "date": "2021-05-23",
        "start": "9:00:00",
        "end": "17:00:00"
      }
    ]
  },
  {
    "id": 104,
    "name": "Donnie",
    "schedule": [
      {
        "date": "2021-05-21",
        "start": "9:00:00",
        "end": "12:00:00"
      },
      {
        "date": "2021-05-22",
        "start": "10:00:00",
        "end": "14:00:00"
      },
      {
        "date": "2021-05-23",
        "start": "9:00:00",
        "end": "17:00:00"
      }
    ]
  },
  {
    "id": 105,
    "name": "JC",
    "schedule": [
      {
        "date": "2021-05-21",
        "start": "9:00:00",
        "end": "12:00:00"
      },
      {
        "date": "2021-05-22",
        "start": "10:00:00",
        "end": "14:00:00"
      },
      {
        "date": "2021-05-23",
        "start": "9:00:00",
        "end": "17:00:00"
      }
    ]
  },
  {
    "id": 106,
    "name": "Louie",
    "schedule": [
      {
        "date": "2021-05-21",
        "start": "9:00:00",
        "end": "12:00:00"
      },
      {
        "date": "2021-05-22",
        "start": "10:00:00",
        "end": "14:00:00"
      },
      {
        "date": "2021-05-23",
        "start": "9:00:00",
        "end": "17:00:00"
      }
    ]
  }
]